{
  "statute": {
    "id": "6f4d129a-11c7-47b8-8ec1-0ddb88d9154e",
    "node_type": "Statute",
    "publisher": "finlex",
    "title": "Laki keskinäisestä virka-avusta verotuksen alalla Suomen ja muiden Euroopan unionin jäsenvaltioiden toimivaltaisten viranomaisten välillä annetun lain 2 §:n muuttamisesta",
    "text": "Laki keskinäisestä virka-avusta verotuksen alalla Suomen ja muiden Euroopan unionin jäsenvaltioiden toimivaltaisten viranomaisten välillä annetun lain 2 §:n muuttamisesta",
    "statute_id": "1220/1994",
    "finlex_url": "https://finlex.fi/fi/laki/ajantasa/1220/1994"
  },
  "chapters": [],
  "sections": [
    {
      "id": "a24df7ea-6120-4277-91e7-2bdd16371ee5",
      "node_type": "Section",
      "publisher": "finlex",
      "title": "2 § Määritelmät",
      "text": "Virka-apudirektiivin 1 artiklassa tarkoitettuja tulo- ja varallisuusveroja ovat Suomessa erityisesti seuraavat verot ja maksut: Tämä laki tulee voimaan 1 päivänä tammikuuta 2006. Verovuodelta 2005 ja sitä edeltäviltä verovuosilta toimitettua varallisuusverotusta koskevien tietojen vaihtoon viranomaisten välillä sovelletaan kuitenkin edelleen tämän lain voimaan tullessa voimassa olleita säännöksiä.",
      "section_number": "2",
      "chapter_number": 1,
      "statute_id": "1220/1994"
    }
  ],
  "clauses": [
    {
      "id": "1d17fd53-8850-4594-9975-9b5a05c03a2d",
      "node_type": "Clause",
      "publisher": "finlex",
      "title": "§ 2 mom 1",
      "text": "1) valtion tuloverot;",
      "clause_number": 1,
      "section_number": "2",
      "statute_id": "1220/1994"
    },
    {
      "id": "c6229984-bb43-466a-8e1b-c5e3271d829d",
      "node_type": "Clause",
      "publisher": "finlex",
      "title": "§ 2 mom 2",
      "text": "2) yhteisön tulovero;",
      "clause_number": 2,
      "section_number": "2",
      "statute_id": "1220/1994"
    },
    {
      "id": "8683506e-e188-4044-8c15-3b8c3540d2d3",
      "node_type": "Clause",
      "publisher": "finlex",
      "title": "§ 2 mom 3",
      "text": "3) kunnallisvero;",
      "clause_number": 3,
      "section_number": "2",
      "statute_id": "1220/1994"
    },
    {
      "id": "7e583689-e8b1-41cd-82f6-231db55e8c08",
      "node_type": "Clause",
      "publisher": "finlex",
      "title": "§ 2 mom 4",
      "text": "4) kirkollisvero;",
      "clause_number": 4,
      "section_number": "2",
      "statute_id": "1220/1994"
    },
    {
      "id": "7aaf11a8-3cb7-423b-8590-b3ed6e825d1f",
      "node_type": "Clause",
      "publisher": "finlex",
      "title": "§ 2 mom 5",
      "text": "5) kansaneläkevakuutusmaksu;",
      "clause_number": 5,
      "section_number": "2",
      "statute_id": "1220/1994"
    },
    {
      "id": "ca27a35e-2311-4276-ba4a-2dfcc398b9b8",
      "node_type": "Clause",
      "publisher": "finlex",
      "title": "§ 2 mom 6",
      "text": "6) sairausvakuutusmaksu;",
      "clause_number": 6,
      "section_number": "2",
      "statute_id": "1220/1994"
    },
    {
      "id": "16bd47a7-9813-49bc-9317-9732ae908d5f",
      "node_type": "Clause",
      "publisher": "finlex",
      "title": "§ 2 mom 7",
      "text": "7) korkotulon lähdevero;",
      "clause_number": 7,
      "section_number": "2",
      "statute_id": "1220/1994"
    },
    {
      "id": "9255bd47-a6d3-4ae6-bc1c-80fbdc1c9515",
      "node_type": "Clause",
      "publisher": "finlex",
      "title": "§ 2 mom 8",
      "text": "8) rajoitetusti verovelvollisen lähdevero;",
      "clause_number": 8,
      "section_number": "2",
      "statute_id": "1220/1994"
    },
    {
      "id": "e84ea248-e104-4841-bc67-de7785353798",
      "node_type": "Clause",
      "publisher": "finlex",
      "title": "§ 2 mom 9",
      "text": "9) kiinteistövero.",
      "clause_number": 9,
      "section_number": "2",
      "statute_id": "1220/1994"
    }
  ],
  "cross_references": [],
  "raw_html_path": "C:\\Users\\danit\\finance-hack\\aalto-hackaton-2026\\data\\raw\\finlex\\Laki\\Laki keskinäisestä virka-avusta verotuksen alalla Suomen ja muiden Euroopan unionin jäsenvaltioiden toimivaltaisten viranomaisten välillä annetun lain 2 §_n muuttamisesta.html"
}