{
  "statute": {
    "id": "5a6cdac0-44e7-43f2-9811-d70c2a0abd97",
    "node_type": "Statute",
    "publisher": "finlex",
    "title": "KHO:1985-B-II-628",
    "text": "KHO:1985-B-II-628",
    "statute_id": "1985/4367",
    "finlex_url": "https://finlex.fi/fi/laki/ajantasa/1985/4367"
  },
  "chapters": [],
  "sections": [
    {
      "id": "ceb4f408-d495-4adf-9824-44603ff0b626",
      "node_type": "Section",
      "publisher": "finlex",
      "title": "KHO:1985-B-II-628",
      "text": "Yhtiön konepaja toimitti yhtiön toiselle tehtaalle laitteita ns. avaimet käteen periaatteella siten, että hankintasopimuksen mukainen koekäyttö ja luovutus tilaajalle hyväksyttiin vuonna 1983. Yhtiön katsottiin ottaneen itsevalmistamansa laitteet käytettäviksi muuhun kuin myyntitarkoitukseen jo konepajalla ennen 1.11.1982, joten yhtiöllä oli oikeus ottaen huomioon eräitä tuotannollisia investointeja koskevista poikkeuksista liikevaihtoverolakiin annetun lain (875/82) voimaantulosäännös, tehdä laitteista eräitä tuotannollisia investointeja koskevista väliaikaisista poikkeuksista liikevaihtoverolakiin annetun lain (848/80) 4 §:n mukainen 1/3 vähennys. L eräitä tuotannollisia investointeja koskevista väliaikaisista poikkeuksista liikevaihtoverolakiin 4 § (848/80) Liikevaihtovero - Kone- ja laiteinvestointivähennys - Voimalaitos - Käsittelyjärjestelmä Paperinvalmistusta harjoittava yhtiö käytti höyryvoimalaitoksessaan polttoaineena puunjalostustoiminnassa kuorimolla ja liettämöllä syntynyttä kuorijätettä ja lietettä höyryenergian kehittämiseen. Koska höyryenergia, jota käytettiin yhtiön teollisuuslaitoksessa, ei ollut liikevaihtoverolain 2 §:n mukaan liikevaihtoverolaissa tarkoitettu tavara, yhtiö ei käyttänyt mainittuja teollisuuden jäteaineita välittömästi tavaran valmistustoiminnassa eikä yhtiö ollut voimalaitostoimintansa osalta liikevaihtoverolain 1 §:ssä tarkoitettu liiketoiminnan harjoittaja. Näin ollen yhtiön ei myöskään katsottu verovelvollisena tai muutoinkaan käyttäneen voimalaitoksessa olevia tai pysyvänä rakennelmana pidettävään kuljetusjärjestelmään kuuluvia kuoren ja lietteen käsittelylaitteita välittömästi tavaran valmistustoiminnassa, joten yhtiöllä ei ollut oikeutta tehdä eräitä tuotannollisia investointeja koskevista poikkeuksista liikevaihtoverolakiin annetun lain 4 §:ssä tarkoitettua vähennystä. Verotus 1/1983. L eräitä tuotannollisia investointeja koskevista poikkeuksista liikevaihtoverolakiin 4 §",
      "section_number": "1",
      "chapter_number": 1,
      "statute_id": "1985/4367"
    }
  ],
  "clauses": [],
  "cross_references": [],
  "raw_html_path": "C:\\Users\\danit\\finance-hack\\aalto-hackaton-2026\\data\\raw\\finlex\\Korkein hallinto-oikeus_ Ennakkopäätökset\\KHO_1985-B-II-628.html"
}