{
  "statute": {
    "id": "29f4d58e-98f1-4053-aea4-996d6f71ad9d",
    "node_type": "Statute",
    "publisher": "finlex",
    "title": "KHO:2021:169",
    "text": "KHO:2021:169",
    "statute_id": "19/0987",
    "finlex_url": "https://finlex.fi/fi/laki/ajantasa/19/0987"
  },
  "chapters": [],
  "sections": [
    {
      "id": "1c8584ed-9d3e-4b07-9741-a2c64a92122a",
      "node_type": "Section",
      "publisher": "finlex",
      "title": "KHO:2021:169",
      "text": "Verohallintoon toimittanut kiinteistöverotukset verovuosilta 2011 - 2016 A Oy:n omistamasta rakennuksesta, joka sijaitsee X:n kaupungissa sijaitsevalla kiinteistöllä. Rakennus muodostuu osarakennuksista 1 ja 2. Rakennuksen verotusarvoa vahvistettaessa jälleenhankinta-arvona on käytetty valtiovarainministeriön rakennusten jälleenhankinta-arvon perusteista annetun asetuksen 14 §:n mukaista toimistorakennuksen jälleenhankinta-arvoa ja ikäalennusprosenttina varojen arvostamisesta verotuksessa annetun lain 30 §:n 1 momentin 1 kohdan mukaista asuin-, toimisto- ja muun niihin verrattavan rakennuksen ikäalennusprosenttia. Verotuksen oikaisulautakuntaon 7.2.2017 tekemillään päätöksillä hylännyt A Oy:n vaatimuksen arvostaa rakennus myymälärakennukseen rinnastettavana rakennuksena jälleenhankinta-arvoa ja rakennuksen vuotuisia ikäalennuksia laskettaessa. Hallinto-oikeuson valituksenalaisella päätöksellään hylännyt A Oy:n valituksen. Hallinto-oikeus on selostettuaan kiinteistöverolain 15 §:n, varojen arvostamisesta verotuksessa annetun lain (arvostamislaki) 28 §:n, 30 §:n 1 momentin 1 ja 2 kohdan, 30 §:n 2 ja 3 momentin sekä valtiovarainministeriön rakennusten jälleenhankinta-arvon perusteista annetun asetuksen (jälleenhankinta-arvoasetus) 1 §:n, 14 §:n, 16 §:n ja 20 §:n säännökset ja asiassa saatua selvitystä perustellut päätöstään seuraavasti: Asiassa on ratkaistavana se, tuleeko yhtiön omistama kylpylähotellirakennus arvostaa vuosien 2011 - 2016 kiinteistöverotuksessa toimistorakennuksia (verotuksessa käytetty) vai myymälärakennuksia (valituksessa vaadittu) koskevien arvostamissääntöjen mukaan. Samoin arvioitavana on se, onko puheena olevan rakennuksen verotusarvoa vahvistettaessa sovellettava arvostamislain 30 §:n 1 momentin 1 vai 2 kohdan ikäalennusprosenttia koskevaa säännöstä. Rakennuksen verotusarvo lasketaan vähentämällä sille määritellystä jälleenhankinta-arvosta sovellettava ikäalennusprosentti. Jälleenhankinta-arvo määritellään valtiovarainministeriön vuosittaisen asetuksen mukaisesti. Ikäalennusprosentti perustuu suoraan arvostamislakiin. Saadun selvityksen mukaan nyt kysymyksessä olevaa rakennusta käytetään hotelli- ja ravintolaliiketiloina sekä kylpylä- ja hyvinvointipalvelutiloina. Kuvattuja toimintoja harjoittava rakennus ei kuulu jälleenhankinta-arvoasetuksessa erikseen lueteltuihin arvostusryhmiin. Rakennus on siten kiinteistöverotuksessa jälleenhankinta-arvoasetuksen 20 §:n mukaisesti arvostettava ensisijaisesti käyttäen lähinnä soveltuvan rakennuksen arvioimisperusteita. Yhtiö on vaatinut, että rakennuksen arvostaminen kiinteistöverotuksessa tulee vahvistaa rakennuksen käyttötarkoituksen, kulumisen ja taloudellisen käyttöiän perusteella. Hallinto-oikeus toteaa, että muun muassa luetellut seikat on otettava huomioon rakennuksen verotusarvoa määritettäessä kiinteistöverotuksessa. Rakennusta käytetään selvityksen mukaan pääasiallisesti hotellitoimintaan ja sen liitännäispalveluihin, kuten ravintola- ja kylpylätoimintaan, mikä vastaa rakennuksen väestötietojärjestelmän mukaista käyttötarkoitusta. Hallinto-oikeus katsoo, että rakennuksen pääkäyttötarkoitus on hotellitoiminta. Hallinto-oikeus toteaa, että vakiintuneen verotuskäytännön mukaan hotellirakennukset on arvostettu toimistorakennuksina. Hallinto-oikeus arvioi, että hotellirakennukset keskimäärin vastaavat paremmin toimistotiloiksi rakennettuja tiloja kuin myymälärakennuksiksi rakennettuja tiloja. Asiaa ei ole yhtiön omistaman kylpylähotellirakennuksen osalta syytä arvioida toisin, eikä yhtiö ole valituksessaan tai asian käsittelyn muissakaan vaiheissa tuonut esiin seikkoja, jotka osoittaisivat rakennuksen vastaavan lähinnä asetuksessa tarkoitettuja myymälärakennuksia. Hallinto-oikeus katsoo siten, että rakennusta on voitu pitää kiinteistöverotuksessa toimistorakennuksena verovuosina 2011 - 2016. Yhtiö on lisäksi vaatinut, että kysymyksessä olevan rakennuksen ikäalennus on laskettava myymälärakennuksia koskevan 4 - 5 prosentin vuotuista ikäalennusprosenttia soveltaen. Yhtiö on perustellut vaatimustaan muun ohella sillä, että hotellirakennukset on rinnastettava myymälärakennuksiin etenkin rakennusten pintamateriaalien ja rakennusten ainesosien kulumiseen, rakennusten käyttöalaan ja rakennusten käyttäjiin liittyvien seikkojen johdosta. Hallinto-oikeus toteaa, että arvostamislain 30 §:ssä ei ole lueteltu tyhjentävästi kaikkia rakennustyyppejä, kuten esimerkiksi hotellirakennusta. Ikäalennusprosenttia arvioitaessa ratkaisu on siten tehtävä kaavamaisin perustein. Huomiota on kiinnitettävä rakennuksen pääasialliseen käyttötarkoitukseen ja siihen, että laissa omaksuttu rakennusten ryhmittely ilmentää käsitystä erityyppisten rakennusten erilaisesta taloudellisesta käyttöiästä. Kysymys on lopulta siitä, kumpaan rakennusten ryhmään, asuin- ja toimistorakennuksiin vai myymälä- ja talousrakennuksiin, hotellirakennus on paremmin rinnastettavissa. Hallinto-oikeus toteaa, että vakiintuneen verotuskäytännön mukaan myös hotellirakennusten ikäalennukset on laskettu toimistorakennuksia koskevaa ikäalennusprosenttia soveltaen. Asiassa saadun selvityksen mukaan etenkin hotellirakennusten pintarakenteisiin ja tekniikkaosiin kohdistuu suurempaa kulutusta kuin toimistorakennusten vastaaviin osiin. Hallinto-oikeus katsoo, että hotellirakennuksen taloudellinen käyttöikä keskimäärin muutoin kuitenkin vastaa paremmin toimistotiloiksi rakennettuja tiloja kuin myymälärakennuksiksi rakennettuja tiloja. Siltä osin kuin yhtiö on esittänyt, että hotellin vuosittaiset kävijämäärät ovat suuret ja asiakaskunta vaihtuu jatkuvasti, hallinto-oikeus toteaa, että majoituskapasiteetti kuitenkin rajaa asiakasmääriä eikä vaihtuvuuden voida sinällään katsoa lisäävän merkittävästi fyysistä kulutusta. Yhtiö ei ole nyt kysymyksessä olevassa asiassa luotettavasti osoittanut, että kylpylähotellin tiloja käyttäisi merkittävästi myös muut kuin hotellivieraat. Kylpylätilojen ja hyvinvointipalveluihin käytettävien tilojen kokonaistilojen määrään suhteutetun vähäisen osuuden vuoksi niiden mahdollisella hotellitilaa suuremmalla kulutuksella ei ole asiassa ratkaisevaa merkitystä. Hallinto-oikeus siten katsoo, että kysymyksessä olevia kylpylähotellitiloja ei voida muun muassa tiloissa käyvien asiakasmäärien aiheuttaman kulumisen perusteella eikä toisaalta myöskään rakennusteknisesti rinnastaa myymälätiloihin. Hallinto-oikeus katsoo edellä todetun johdosta, että yhtiön omistamaa kylpylähotellirakennusta ei myöskään ikäalennusprosenttia arvioitaessa voida rinnastaa myymälä- ja talousrakennukseksi vaan asuin- ja toimistorakennukseksi. Siten kyseistä kylpylähotellirakennusta on ikäalennusta laskettaessa pidettävä asuin- ja toimistorakennuksiin verrattavana rakennuksena ja rakennuksen verotusarvoa laskettaessa on tullut soveltaa arvostamislain 30 §:n 1 momentin 1 kohdan ikäalennusprosenttia koskevaa säännöstä. Edellä mainituilla perusteilla hallinto-oikeus katsoo, että oikaisulautakunnan päätöksiä ei ole aihetta muuttaa. A Oyon pyytänyt lupaa valittaa hallinto-oikeuden päätöksestä ja valituksessaan vaatinut, että kiinteistöllä sijaitseva rakennus on arvostettava verovuosien 2011 - 2016 kiinteistöverotuksissa myymälärakennuksiin rinnastettavana jälleenhankinta-arvoa ja ikäalennuksia määritettäessä. Vaatimusten tueksi on esitetty muun ohella seuraavaa: Rakennus koostuu kahdesta osarakennuksesta, alkuperäisestä kylpylähotellista ja sen laajennusosasta. Alkuperäisessä osassa on kylpylä-, majoitus-, ravintola- ja muita oheispalvelujen tiloja. Pienempi lisäosa on pääasiassa majoituskäytössä. Liiketoiminta-ajatuksen näkökulmasta kyse ei ole ollut hotellitoiminnasta vaan kylpylätoiminnasta. Alkuperäisessä rakennuksessa tiloista selvästi suurempi osa oli kylpylän ja sen oheistoimintojen käytössä ja vähäisempi osa majoituskäytössä. Majoitustilojen yhteenlaskettu pinta-ala on lisärakennuksen jälkeen edelleen pienempi kuin kylpylätoimintaan kuuluvien tilojen pinta-ala. Osarakennusten välillä voidaan perustellusti sanoa olevan selvä ero käytön tai käyttötarkoituksen suhteen sikäli, että osarakennus 1:n pinta-alasta yli puolet on kylpylän ja sen oheistoimintojen käytössä, jolloin osarakennus 1 on ”parhaiten myymälärakennusta vastaava”. Osarakennus 2 on majoitus- tai hotellikäytössä. Kylpylähotellikäytössä olevaan osarakennukseen kohdistuu muun muassa suurten käyttäjämäärien, kylpylätoiminnan vaatiman teknisen laitteiston ja eri palveluiden vaatiman tavaralogistiikan johdosta tuntuvasti suurempaa kulumista kuin tavanomaiseen toimistorakennukseen. Jos luokitus perustuu osarakennuksiin, osarakennus 1 on parhaiten myymälään rinnastuva ja osarakennus 2 ilmeisesti paremmin toimistoon kuin myymälään rinnastuva. Jos alkuperäinen rakennus ja lisärakennus on käsiteltävä kumpikin omina rakennuksinaan, luokitus on sama kuin edellisessä vaihtoehdossa. Jos rakennus luokitellaan yhtenä kokonaisuutena, ja perustetaan luokitus pääasialliseksi katsottavaan käyttötarkoitukseen, vastaa rakennus parhaiten myymälärakennusta. Veronsaajien oikeudenvalvontayksikköon antanut vastineen, jossa on vaadittu valituksen hylkäämistä ja esitetty muun ohella seuraavaa: Oikeudenvalvontayksikkö katsoo ensisijaisesti, että kylpylätoiminta on hotellitoiminnan liitännäispalvelu. Sillä seikalla, että kylpylätilojen pinta-ala on kohtalaisen suuri, ei ole lähtökohtaisesti merkitystä käsillä olevan asian ratkaisemisessa. Toissijaisesti oikeudenvalvontayksikkö katsoo, että kylpylätoimintojen osuus on joko noin 23 prosenttia rakennusosasta 1 tai noin 19 prosenttia koko rakennuksesta. Kiinteistöverotuksessa on olennaista se, minkä tyyppisestä rakennuksesta on kyse ja mitkä ovat sen ominaisuudet. Käsillä olevaan asiaan liittyvä rakennus rinnastuu ominaisuuksiensa puolesta paremmin toimistorakennuksiin kuin myymälärakennuksiin eikä sen voida katsoa poikkeavan muista hotellitoiminnan tarkoitukseen rakennetuista ja käytetyistä rakennuksista. A Oyon antanut vastaselityksen, joka on annettu tiedoksiVeronsaajien oikeudenvalvontayksikölle.",
      "section_number": "1",
      "chapter_number": 1,
      "statute_id": "19/0987"
    }
  ],
  "clauses": [],
  "cross_references": [
    {
      "raw_text": "§ 1 momentti\nL",
      "statute_id": "19/0987",
      "section_number": "1 momentti\nL",
      "clause_number": null,
      "resolution_confidence": 0.0
    },
    {
      "raw_text": "§ 1 momentti",
      "statute_id": "19/0987",
      "section_number": "1 momentti",
      "clause_number": null,
      "resolution_confidence": 0.0
    }
  ],
  "raw_html_path": "C:\\Users\\danit\\finance-hack\\aalto-hackaton-2026\\data\\raw\\finlex\\Korkein hallinto-oikeus_ Ennakkopäätökset\\KHO_2021_169.html"
}