{
  "statute": {
    "id": "fea77438-ee5f-4773-8d3a-3796ad819fe4",
    "node_type": "Statute",
    "publisher": "finlex",
    "title": "Valtioneuvoston asetus työtuomioistuimesta annetun asetuksen muuttamisesta",
    "text": "Valtioneuvoston asetus työtuomioistuimesta annetun asetuksen muuttamisesta",
    "statute_id": "201/1983",
    "finlex_url": "https://finlex.fi/fi/laki/ajantasa/201/1983"
  },
  "chapters": [],
  "sections": [
    {
      "id": "dbe5a170-efab-4562-809f-48f5ca10b3fc",
      "node_type": "Section",
      "publisher": "finlex",
      "title": "7 §",
      "text": "Virkavapautta presidentille ja työtuomioistuinneuvokselle myöntää oikeusministeriö. Tämä asetus tulee voimaan 12 päivänä heinäkuuta 2000.",
      "section_number": "7",
      "chapter_number": 1,
      "statute_id": "201/1983"
    }
  ],
  "clauses": [],
  "cross_references": [],
  "raw_html_path": "C:\\Users\\danit\\finance-hack\\aalto-hackaton-2026\\data\\raw\\finlex\\Asetus\\Valtioneuvoston asetus työtuomioistuimesta annetun asetuksen muuttamisesta_2.html"
}