{
  "statute": {
    "id": "b4b49988-b092-433c-8dc5-3dac003c0caf",
    "node_type": "Statute",
    "publisher": "finlex",
    "title": "Konsulipalvelulaki",
    "text": "Konsulipalvelulaki",
    "statute_id": "50/1980",
    "finlex_url": "https://finlex.fi/fi/laki/ajantasa/50/1980"
  },
  "chapters": [
    {
      "id": "ac6877ee-bc44-482b-8889-274bba63a073",
      "node_type": "Chapter",
      "publisher": "finlex",
      "title": "Chapter 1",
      "text": "1 luku Yleiset säännökset",
      "chapter_number": 1,
      "statute_id": "50/1980"
    },
    {
      "id": "d3d04f22-dc89-4078-befc-a9c5b8b24d40",
      "node_type": "Chapter",
      "publisher": "finlex",
      "title": "Chapter 2",
      "text": "2 luku Hallinto",
      "chapter_number": 2,
      "statute_id": "50/1980"
    },
    {
      "id": "f7a22339-cab9-4473-af45-cf27c66c3335",
      "node_type": "Chapter",
      "publisher": "finlex",
      "title": "Chapter 3",
      "text": "3 luku Palvelut hädänalaisessa asemassa olevalle",
      "chapter_number": 3,
      "statute_id": "50/1980"
    },
    {
      "id": "8e724a76-9367-4ee4-a8e9-832a599875ad",
      "node_type": "Chapter",
      "publisher": "finlex",
      "title": "Chapter 4",
      "text": "4 luku Palvelut kriisitilanteessa",
      "chapter_number": 4,
      "statute_id": "50/1980"
    },
    {
      "id": "fea0b1e4-810c-439b-ab07-787f0aa3b5bc",
      "node_type": "Chapter",
      "publisher": "finlex",
      "title": "Chapter 5",
      "text": "5 luku Palvelut vapautensa menettäneelle ja syytetylle",
      "chapter_number": 5,
      "statute_id": "50/1980"
    },
    {
      "id": "de474fdd-bc4f-4088-8553-74ccd5ae69aa",
      "node_type": "Chapter",
      "publisher": "finlex",
      "title": "Chapter 6",
      "text": "6 luku Palvelut kuolemantapauksessa",
      "chapter_number": 6,
      "statute_id": "50/1980"
    },
    {
      "id": "5596ebe9-fbcd-484d-a2c5-887164776598",
      "node_type": "Chapter",
      "publisher": "finlex",
      "title": "Chapter 7",
      "text": "7 luku Palvelut jäämistöasioissa",
      "chapter_number": 7,
      "statute_id": "50/1980"
    },
    {
      "id": "1f7e67b0-196b-4bb3-8a3c-d5e161c98950",
      "node_type": "Chapter",
      "publisher": "finlex",
      "title": "Chapter 8",
      "text": "8 luku Palvelut yksityistä henkilöä koskevien tietojen hankkimiseksi",
      "chapter_number": 8,
      "statute_id": "50/1980"
    },
    {
      "id": "42173260-ab14-4ea2-abcd-ff95d3cdec82",
      "node_type": "Chapter",
      "publisher": "finlex",
      "title": "Chapter 9",
      "text": "9 luku Palvelut lapsen palauttamiseksi",
      "chapter_number": 9,
      "statute_id": "50/1980"
    },
    {
      "id": "3762b536-6a02-4046-be11-158d527391c6",
      "node_type": "Chapter",
      "publisher": "finlex",
      "title": "Chapter 10",
      "text": "10 luku Notaaripalvelut",
      "chapter_number": 10,
      "statute_id": "50/1980"
    },
    {
      "id": "794577f8-0cf5-42b8-bf76-2416f780dc21",
      "node_type": "Chapter",
      "publisher": "finlex",
      "title": "Chapter 11",
      "text": "11 luku Henkilötietojen käsittely kriisitilanteessa",
      "chapter_number": 11,
      "statute_id": "50/1980"
    },
    {
      "id": "d255b069-398f-4ded-a576-9acd57e406a6",
      "node_type": "Chapter",
      "publisher": "finlex",
      "title": "Chapter 12",
      "text": "12 luku Erinäiset säännökset",
      "chapter_number": 12,
      "statute_id": "50/1980"
    }
  ],
  "sections": [
    {
      "id": "abf2f42a-3190-4260-88f5-00c6f514376b",
      "node_type": "Section",
      "publisher": "finlex",
      "title": "1 § Soveltamisala",
      "text": "Tässä laissa konsulipalveluilla tarkoitetaan konsulisuhteita koskevan Wienin yleissopimuksen (SopS 50/1980) 5 artiklassa mainittuja sellaisia konsulitehtäviä, joita Suomen ulkomaanedustukseen kuuluvat diplomaattiset edustustot ja konsuliedustustot (edustusto) voivat suorittaa yksityisen henkilön tai yhteisön avustamiseksi tai niiden etujen ja oikeuksien valvomiseksi ja joiden suorittaminen kuuluu ulkoasiainhallinnon tehtäviin tämän lain nojalla, jollei palvelun antamisesta toisin säädetä tai määrätä.",
      "section_number": "1",
      "chapter_number": 1,
      "statute_id": "50/1980"
    },
    {
      "id": "2f950e49-6d4e-4ea0-bee5-aa6dbc299aee",
      "node_type": "Section",
      "publisher": "finlex",
      "title": "2 § Konsulipalvelun saaja",
      "text": "Jos konsulipalvelun antamisesta ei toisin säädetä, tämän lain 3―10 luvussa tarkoitettuja konsulipalveluja annetaan suomalaiselle yhteisölle sekä henkilölle, joka on Suomen kansalainen taikka sellainen Suomessa pysyvästi asuva ulkomaalainen, jolla on oikeus tai jolle on myönnetty lupa oleskeluun tai työntekoon pysyvässä tai siihen verrattavassa tarkoituksessa Suomessa. Pohjoismaan kansalaiselle annettavista palveluista määrätään Islannin, Norjan, Ruotsin, Suomen ja Tanskan välillä tehdyn yhteistyösopimuksen (SopS 28/1962) 34 artiklassa. Euroopan unionin kansalaisen oikeudesta saada palveluja toisen jäsenvaltion diplomaatti- ja konsuliviranomaisilta määrätään Euroopan yhteisön perustamissopimuksen 8 c artiklassa. Tämän lain 4 ja 10 luvussa tarkoitettuja konsulipalveluja voidaan antaa erityisestä syystä myös muulle ulkomaalaiselle. Ulkomaiselle yhteisölle voidaan erityisestä syystä antaa 10 luvussa tarkoitettuja konsulipalveluja.",
      "section_number": "2",
      "chapter_number": 1,
      "statute_id": "50/1980"
    },
    {
      "id": "2cf1a065-7562-42ef-b904-d3592ba95550",
      "node_type": "Section",
      "publisher": "finlex",
      "title": "3 § Virka-apu",
      "text": "Ulkoasiainministeriö ja edustustot antavat pyynnöstä virka-apua Suomen viranomaiselle, jos siitä on erikseen säädetty tai jos virka-avun antamista voidaan muutoin pitää perusteltuna.",
      "section_number": "3",
      "chapter_number": 1,
      "statute_id": "50/1980"
    },
    {
      "id": "c866a4fb-011b-4876-bf7a-5fce24e0c448",
      "node_type": "Section",
      "publisher": "finlex",
      "title": "4 § Yleinen etujen ja oikeuksien seuranta",
      "text": "Ulkoasiainministeriö ja edustustot seuraavat yleisesti 2 §:n 1 momentissa tarkoitettutujen henkilöiden ja yhteisöjen etujen ja oikeuksien toteutumista ulkomailla ottaen huomioon kansainvälisesti hyväksytyt ihmisoikeudet ja muut kansainväliset velvoitteet.",
      "section_number": "4",
      "chapter_number": 1,
      "statute_id": "50/1980"
    },
    {
      "id": "feac87a2-86ef-438d-af0e-163fefb85678",
      "node_type": "Section",
      "publisher": "finlex",
      "title": "5 § Yleinen neuvonta",
      "text": "Ulkoasiainministeriö ja edustustot antavat 2 §:n 1 momentissa tarkoitetuille henkilöille ja yhteisöille mahdollisuuksien mukaan yleistä neuvontaa edustuston toimipiirin erityisolosuhteista sekä asioissa, jotka liittyvät etuja ja oikeuksia koskevien asioiden hoitamiseen vieraan valtion viranomaisessa.",
      "section_number": "5",
      "chapter_number": 1,
      "statute_id": "50/1980"
    },
    {
      "id": "7df85aea-dbb0-4fc7-9a39-8cc90d8e158f",
      "node_type": "Section",
      "publisher": "finlex",
      "title": "6 § Konsulipalveluja koskevat yleiset rajoitukset",
      "text": "Ulkoasiainministeriön ja edustustojen tulee hoitaa konsulipalvelut ottaen huomioon edustuston toimipiirin lait ja määräykset, yleinen kansainvälinen oikeus sekä Suomea sitovat kansainväliset sopimukset. Ulkoasiainministeriö, edustusto tai niiden henkilökuntaan kuuluva ei voi toimia konsulipalvelua hakevan oikeudenkäyntiavustajana tai -asiamiehenä taikka oikeudellisena neuvonantajana.",
      "section_number": "6",
      "chapter_number": 1,
      "statute_id": "50/1980"
    },
    {
      "id": "0eb52b36-6027-4744-9861-b823e35985f7",
      "node_type": "Section",
      "publisher": "finlex",
      "title": "7 § Neuvonnan ensisijaisuus ja hakijan tiedonantovelvollisuus",
      "text": "Ennen tässä laissa tarkoitettuihin muihin toimenpiteisiin ryhtymistä konsulipalvelun hakijaa neuvotaan ja ohjataan asiansa hoitamiseksi. Tämän lain 3―10 luvussa tarkoitettuhin toimenpiteisiin voidaan ryhtyä, jos hakijan ei muutoin ole mahdollista hoitaa asiaansa. Hakijan on annettava ulkoasiainministeriölle ja edustustolle tietoja ja selvityksiä, jotka ovat tarpeen konsulipalvelun antamiseksi sekä muutoinkin edistettävä palvelun antamista asiassaan.",
      "section_number": "7",
      "chapter_number": 1,
      "statute_id": "50/1980"
    },
    {
      "id": "7783e84c-add4-4fb3-8c30-d5f80221368c",
      "node_type": "Section",
      "publisher": "finlex",
      "title": "8 § Ulkoasiainministeriön tehtävät",
      "text": "Konsulipalveluja koskeva yleinen suunnittelu, ohjaus ja valvonta kuuluvat ulkoasiainministeriölle. Ulkoasiainministeriö neuvoo, ohjaa ja avustaa tarpeen mukaan edustustoa yksittäisen konsulipalvelun hoitamisessa.",
      "section_number": "8",
      "chapter_number": 2,
      "statute_id": "50/1980"
    },
    {
      "id": "03e2950d-fa4c-4121-a627-53f724688223",
      "node_type": "Section",
      "publisher": "finlex",
      "title": "9 § Konsulipalvelujen hoitaminen edustustossa",
      "text": "Konsulipalveluja hoitavia edustustoja ovat suurlähetystöt, lähetystöt ja lähetetyn pääkonsulin, konsulin ja varakonsulin virastot. Edustuston päällikön tehtävänä on valvoa edustuston toimipiirissä konsulipalvelujen hoitamista ja vastata niiden antamisesta. Jos konsulipalvelua tarvitaan maassa, joka ei kuulu minkään edustuston toimipiiriin, ulkoasiainministeriö määrää konsulipalvelun hoitamisesta.",
      "section_number": "9",
      "chapter_number": 2,
      "statute_id": "50/1980"
    },
    {
      "id": "ee0718a5-1a70-4768-9606-99aaac5bb9e2",
      "node_type": "Section",
      "publisher": "finlex",
      "title": "10 § Kunniakonsulit",
      "text": "Kunniakonsuli voi hoitaa niitä konsulipalveluja, jotka hänelle kuuluvat tehtävänsä mukaisesti tai joita hoitamaan ulkoasiainministeriö on hänet valtuuttanut.",
      "section_number": "10",
      "chapter_number": 2,
      "statute_id": "50/1980"
    },
    {
      "id": "8070887b-9a5b-40f9-ae55-0239b39c22ff",
      "node_type": "Section",
      "publisher": "finlex",
      "title": "11 § Hädänalaisessa asemassa oleva",
      "text": "Tässä luvussa säädettyjä konsulipalveluja voidaan antaa sellaiselle tilapäisesti ulkomailla edustuston toimipiirissä oleskelevalle 2 §:n 1 momentissa tarkoitetulle henkilölle, jonka edustusto on todennut olevan hädänalaisessa asemassa sairauden, tapaturman, onnettomuuden, rikoksen kohteeksi joutumisen tai muun näihin rinnastettavan syyn vuoksi.",
      "section_number": "11",
      "chapter_number": 3,
      "statute_id": "50/1980"
    },
    {
      "id": "be166b49-0de1-4ea4-8453-d09a9f732f42",
      "node_type": "Section",
      "publisher": "finlex",
      "title": "12 § Hädänalaisessa asemassa olevan avustaminen",
      "text": "Edustusto neuvoo ja avustaa hädänalaisessa asemassa olevaa tarpeen mukaan yhteyden saamiseksi hänen lähiomaiseensa tai muuhun henkilöön, sairaanhoidon saamiseksi, Suomeen kotiuttamisen järjestämiseksi, oikeusavun saamiseksi, rikosilmoituksen tekemiseksi sekä välttämättömän, tilanteen vaatiman muun avun saamiseksi. Jos hädänalainen asema johtuu siitä, että henkilö on joutunut oikeudettoman vapaudenriiston kohteeksi, edustuston tulee lisäksi välittää tieto asiasta toimivaltaiselle viranomaiselle asianomaisessa valtiossa ja asianomaiselle Suomen viranomaiselle, avustaa tarpeen mukaan tietojen välittämisessä asiaa hoitavien viranomaisten ja oikeudettoman vapaudenriiston kohteeksi joutuneen välillä, avustaa välttämättömässä yhteydenpidossa asianomaisen ja hänen lähiomaisensa välillä sekä seurata asian hoitamista asianomaisen valtion viranomaisessa.",
      "section_number": "12",
      "chapter_number": 3,
      "statute_id": "50/1980"
    },
    {
      "id": "c1fc6bc6-effd-4f77-8a03-57f10c469e7a",
      "node_type": "Section",
      "publisher": "finlex",
      "title": "13 § Varojen välittäminen ja taloudellinen avustaminen",
      "text": "Edustusto voi hakemuksesta välittää varoja ulkoasiainministeriön tilille etukäteen tehtyä talletusta vastaan tai myöntää taloudellista avustusta tarkoitukseen varattujen määrärahojen puitteissa hädänalaisessa asemassa olevalle henkilölle, jonka edustusto on todennut olevan kykenemätön ilman sen apua saamaan riittäviä varoja käyttöönsä välittömän hädän poistamiseksi. Taloudellisena avustuksena edustusto voi myöntää: Vähäisen taloudellisen avustuksen arvo vähennetään edustuston mahdollisesti välittämistä varoista tai lisätään mahdollisesti tehtävään takaisinmaksusitoumukseen.",
      "section_number": "13",
      "chapter_number": 3,
      "statute_id": "50/1980"
    },
    {
      "id": "994ee872-bd4e-4230-b012-ebbecc5ac910",
      "node_type": "Section",
      "publisher": "finlex",
      "title": "14 § Taloudellisen avustuksen epääminen",
      "text": "Edustusto voi evätä taloudellisen avustuksen myöntämisen, jos:",
      "section_number": "14",
      "chapter_number": 3,
      "statute_id": "50/1980"
    },
    {
      "id": "898a6f93-646f-416b-ab89-8bf2206ad018",
      "node_type": "Section",
      "publisher": "finlex",
      "title": "15 § Henkilökohtainen turvallisuus",
      "text": "Suuronnettomuuden, luonnononnettomuuden, ympäristöonnettomuuden, sodan, sisällissodan tai muun kriisitilanteen sattuessa tai uhatessa edustusto avustaa toimipiirissään oleskelevaa 2 §:n 1 momentissa tarkoitettua henkilöä hänen henkilökohtaisen turvallisuutensa suojaamiseksi.",
      "section_number": "15",
      "chapter_number": 4,
      "statute_id": "50/1980"
    },
    {
      "id": "84746cc9-a2af-4796-bdc7-b390ff9b303b",
      "node_type": "Section",
      "publisher": "finlex",
      "title": "16 § Evakuointi ja kotiuttaminen",
      "text": "Jos asianomaisen henkilökohtaisen turvallisuuden suojaaminen edellyttää, edustusto voi avustaa evakuoinnin järjestämisessä kriisialueelta lähimmälle turvalliselle alueelle tai kotimaahan. Evakuoinnin ja kotiuttamisen järjestämiseen ryhdytään ainoastaan asianomaisen suostumuksella.",
      "section_number": "16",
      "chapter_number": 4,
      "statute_id": "50/1980"
    },
    {
      "id": "dc325537-bab9-4fb3-ad4b-7dee8af4eb64",
      "node_type": "Section",
      "publisher": "finlex",
      "title": "17 § Avustamisessa huomioon otettavat tekijät",
      "text": "Edellä 15 ja 16 §:ssä tarkoitettuja avustamistoimenpiteitä ja niiden laajuutta harkittaessa sekä toimenpiteitä toteutettaessa otetaan huomioon kriisitilanne, muut olosuhteet, muiden Pohjoismaiden ja Euroopan unionin jäsenvaltioiden toimenpiteet sekä edustuston tosiasialliset mahdollisuudet avustamiseen.",
      "section_number": "17",
      "chapter_number": 4,
      "statute_id": "50/1980"
    },
    {
      "id": "2ba1a1e7-aef8-4c25-bd4b-74ddb8b88fdd",
      "node_type": "Section",
      "publisher": "finlex",
      "title": "18 § Yhteydenpito ja tiedon välittäminen",
      "text": "Edustusto avustaa mahdollisuuksien mukaan kriisitilanteessa tai sen uhatessa välttämättömässä yhteydenpidossa asianomaisen ja hänen kotimaassa olevan lähiomaisensa välillä. Edustusto välittää tietoja ulkoasiainministeriölle kriisialueella olevista 2 §:n 1 momentissa tarkoitetuista henkilöistä ja kriisitilanteen kehittymisestä. Ulkoasiainministeriö tai edustusto voivat harkintansa mukaan tiedottaa tietylle alueelle matkustamista, siellä oleskelua tai alueelta poistumista koskevista olosuhteista.",
      "section_number": "18",
      "chapter_number": 4,
      "statute_id": "50/1980"
    },
    {
      "id": "e00dfb4f-48de-410c-a94c-56f4824e4573",
      "node_type": "Section",
      "publisher": "finlex",
      "title": "19 § Vapautensa menettäneen välitön avustaminen",
      "text": "Jos edustuston toimipiirissä rikoksesta epäiltynä pidätetty, vangittu tai muulla tavoin vapautensa menettänyt taikka vapausrangaistusta suorittava 2 §:n 1 momentissa tarkoitettu henkilö (vapautensa menettänyt) pyytää, on edustuston viipymättä otettava yhteyttä häneen. Vapautensa menettäneen pyynnöstä tieto vapauden menetyksestä välitetään hänen lähiomaiselleen tai muulle nimetylle henkilölle, hänen luonaan vieraillaan mahdollisuuksien mukaan ja häntä avustetaan tarpeen mukaan oikeusavustajan ja muun paikallisen lainsäädännön mukaisen oikeusavun sekä tulkin saamiseksi.",
      "section_number": "19",
      "chapter_number": 5,
      "statute_id": "50/1980"
    },
    {
      "id": "51187d4d-688a-4ac1-b660-ebecf75dfc59",
      "node_type": "Section",
      "publisher": "finlex",
      "title": "20 § Avustaminen vapauden menetyksen aikana",
      "text": "Vapauden menetyksen aikana edustusto pitää yhteyttä vapautensa menettäneeseen tarpeen ja paikallisten olosuhteiden mukaan. Edustusto seuraa vapautensa menettäneen kohtelua ja asian hoitamista vieraan valtion viranomaisessa. Edustusto voi harkintansa mukaan avustaa vapautensa menettänyttä hänen pyynnöstään armahduksen tai ennenaikaisen vapautuksen hakemiseksi taikka vapausrangaistuksen täytäntöönpanon siirtämiseksi.",
      "section_number": "20",
      "chapter_number": 5,
      "statute_id": "50/1980"
    },
    {
      "id": "3862350e-a65c-4496-bf56-214323fd3ab1",
      "node_type": "Section",
      "publisher": "finlex",
      "title": "21 § Varojen välittäminen vapautensa menettäneelle",
      "text": "Edustusto voi välittää ulkoasiainministeriön tilille etukäteen tehtyä talletusta vastaan varoja vapautensa menettäneelle vapautumisen ehdoksi määrättyjen sakkojen tai takuusumman maksamiseksi.",
      "section_number": "21",
      "chapter_number": 5,
      "statute_id": "50/1980"
    },
    {
      "id": "cff4cf88-4555-490a-a293-ad500ed766e2",
      "node_type": "Section",
      "publisher": "finlex",
      "title": "22 § Syytetyn avustaminen",
      "text": "Jos rikoksesta syytetty ei ole menettänyt vapauttaan, edustusto avustaa syytettyä hänen pyynnöstään tarpeen mukaan oikeusavustajan ja muun paikallisen lainsäädännön mukaisen oikeusavun ja tulkin saamiseksi sekä pitää tarpeen mukaan yhteyttä syytettyyn.",
      "section_number": "22",
      "chapter_number": 5,
      "statute_id": "50/1980"
    },
    {
      "id": "7b136609-c12d-47b4-9b06-c7157b9cd3a1",
      "node_type": "Section",
      "publisher": "finlex",
      "title": "23 § Kuolemantapauksesta ilmoittaminen",
      "text": "Jos edustusto on saanut ilmoituksen toimipiirissään kuolleesta 2 §:n 1 momentissa tarkoitetusta henkilöstä, edustusto ilmoittaa kuolemantapauksesta ulkoasiainministeriölle. Tieto kuolemantapauksesta välitetään myös vainajan lähiomaiselle tai muulle läheiselle henkilölle, jonka henkilöllisyys ja olinpaikka ovat kohtuudella selvitettävissä.",
      "section_number": "23",
      "chapter_number": 6,
      "statute_id": "50/1980"
    },
    {
      "id": "23adc678-6413-4165-b8f2-6a83490ccb90",
      "node_type": "Section",
      "publisher": "finlex",
      "title": "24 § Vainajan hautaaminen, tuhkaaminen ja kotiuttaminen",
      "text": "Edustusto voi ryhtyä toimenpiteisiin vainajan hautaamisen, tuhkaamisen tai Suomeen kotiuttamisen järjestämiseksi lähiomaisen pyynnöstä. Jos vainajan lähiomainen ei huolehdi vainajan hautaamisesta, tuhkaamisesta tai Suomeen kotiuttamisesta, edustusto ottaa yhteyttä paikalliseen viranomaiseen vainajan hautaamiseksi tai tuhkaamiseksi paikallisen käytännön mukaisesti.",
      "section_number": "24",
      "chapter_number": 6,
      "statute_id": "50/1980"
    },
    {
      "id": "e333a9a3-b033-4f4d-bd12-05e378067e42",
      "node_type": "Section",
      "publisher": "finlex",
      "title": "25 § Selvityksen hankkiminen kuolemansyystä",
      "text": "Edustusto avustaa lähiomaisen pyynnöstä vainajan kuolintodistuksen tai muun kuolemansyyn selvityksen hankkimisessa, jos selvityksen hankkiminen ei muutoin ole mahdollista.",
      "section_number": "25",
      "chapter_number": 6,
      "statute_id": "50/1980"
    },
    {
      "id": "5678974c-2895-465d-999f-5b6a99e7cfab",
      "node_type": "Section",
      "publisher": "finlex",
      "title": "26 § Jäämistön ilmoittaminen perilliselle",
      "text": "Jos edustusto saa tiedon viranomaiselta tai muulla tavoin jäämistöstä, johon 2 §:n 1 momentissa tarkoitetulla henkilöllä voi olla perintöoikeus, edustusto ilmoittaa siitä ulkoasiainministeriölle. Ulkoasiainministeriö välittää tiedon jäämistöstä Suomessa asuvalle perilliselle tai muulle asianosaiselle, jonka henkilöllisyys ja olinpaikka ovat kohtuudella selvitettävissä. Edustusto ei kuitenkaan ilmoita jäämistöstä, jos jäämistö on otettu sen sijaintipaikkakunnalla perillisen tai muun siihen oikeutetun haltuun tai perillinen tai muu siihen oikeutettu on ryhtynyt hoitamaan jäämistöä.",
      "section_number": "26",
      "chapter_number": 7,
      "statute_id": "50/1980"
    },
    {
      "id": "7e29c8f3-0eed-4fd7-b56b-c86243b76c8d",
      "node_type": "Section",
      "publisher": "finlex",
      "title": "27 § Jäämistöasioihin liittyvät muut tehtävät",
      "text": "Jos Suomessa asuvalla 2 §:n 1 momentissa tarkoitulla henkilöllä on ilmeisesti perintöoikeus ulkomailla olevaan jäämistöön, edustusto voi asianomaisen pyynnöstä tiedustella toimipiirinsä viranomaisilta, sijaitseeko jäämistö edustuston toimipiirissä sekä kenen hoidossa jäämistö on. Edustusto avustaa tarvittaessa perillisiä pesänhoitajan saamisessa edustuston toimipiirissä sijaitsevan jäämistön hoitamiseksi.",
      "section_number": "27",
      "chapter_number": 7,
      "statute_id": "50/1980"
    },
    {
      "id": "bc8e86fd-f7b5-440a-90bf-a47262896649",
      "node_type": "Section",
      "publisher": "finlex",
      "title": "28 § Kadonneeksi epäilty ja epäillyn rikoksen kohteeksi joutunut",
      "text": "Edustusto voi perustellusta syystä tiedustella sellaisen ulkomailla tilapäisesti oleskelevan 2 §:n 1 momentissa tarkoitetun henkilön olosuhteita ja olinpaikkaa, jonka hänen huoltajansa tai lähiomaisensa epäilee kadonneen tai joutuneen rikoksen kohteeksi edustuston toimipiirissä. Edustusto tekee tiedustelun huoltajan tai lähiomaisen pyynnöstä ja ensisijaisesti toimipiirinsä viranomaisten välityksellä. Edustusto voi ilmoittaa tiedustelijalle täysi-ikäisestä henkilöstä saamansa tiedot vain asianomaisen suostumuksella. Suostumuksen puuttuessa edustusto voi ilmoittaa saamansa tiedot, jos on erittäin todennäköistä, että asianomainen olisi suostumuksensa antanut.",
      "section_number": "28",
      "chapter_number": 8,
      "statute_id": "50/1980"
    },
    {
      "id": "2310036e-bf29-4530-81ab-53b4f80a5f66",
      "node_type": "Section",
      "publisher": "finlex",
      "title": "29 § Lapsen olosuhteita koskeva tiedustelu",
      "text": "Edustusto voi tehdä ulkomailla tilapäisesti oleskelevan 2 §:n 1 momentissa tarkoitetun lapsen olosuhteita koskevan tiedustelun hänen huoltajansa pyynnöstä, jos on perusteltua syytä epäillä, että lapsen olosuhteet vaarantavat tai uhkaavat vaarantaa lapsen terveyttä. Edustusto tekee tiedustelun ensisijaisesti toimipiirinsä viranomaisten välityksellä.",
      "section_number": "29",
      "chapter_number": 8,
      "statute_id": "50/1980"
    },
    {
      "id": "a813e15f-5bf4-4c1f-8336-6f11d39965d6",
      "node_type": "Section",
      "publisher": "finlex",
      "title": "30 § Henkilöä koskevan asiakirjan tai osoitetiedon hankkiminen",
      "text": "Edustusto voi sille tai ulkoasiainministeriölle tehdyn kirjallisen hakemuksen saatuaan hankkia toimipiiristään virkatodistuksia tai muita henkilöä koskevia asiakirjoja sekä osoitetietoja, jos asiakirjan tai osoitetiedon hankkiminen on perusteltua hakemuksen tehneen 2 §:n 1 momentissa tarkoitetun henkilön tai yhteisön etujen, oikeuksien tai velvollisuuksien toteuttamiseksi.",
      "section_number": "30",
      "chapter_number": 8,
      "statute_id": "50/1980"
    },
    {
      "id": "3275e8fd-7706-4b87-8916-b8a01f128c7c",
      "node_type": "Section",
      "publisher": "finlex",
      "title": "31 § Edellytykset toimenpiteille lapsen palauttamiseksi",
      "text": "Edustusto avustaa lapsen palauttamisessa Suomeen, kun lapsen poisvienti Suomesta vieraaseen valtioon tai palauttamatta jättäminen vieraasta valtiosta Suomeen on luvatonta lapsen huollosta ja tapaamisoikeudesta annetun lain (361/1983) nojalla eikä lapsen palauttamista koskevan asian hoitaminen kuulu muun viranomaisen toimivaltaan lain, asetuksen taikka Suomea sitovan kansainvälisen sopimuksen perusteella. Jos edustuston toimipiirissä pysyvästi asuva alle 16-vuotias lapsi on viety toisen edustuston toimipiiriin tai on jätetty sieltä palauttamatta, edustusto avustaa lapsen palauttamisessa:",
      "section_number": "31",
      "chapter_number": 9,
      "statute_id": "50/1980"
    },
    {
      "id": "ff77822b-fd67-45c0-a1cc-4c2540cb5193",
      "node_type": "Section",
      "publisher": "finlex",
      "title": "32 § Toimenpiteet lapsen palauttamiseksi",
      "text": "Edellä 31 §:ssä säädettyjen edellytysten täyttyessä edustusto voi tarpeen mukaan ryhtyä 2―5 momentissa säädettyihin toimenpiteisiin lapsen palauttamiseksi. Edustusto pyrkii edistämään lapsen vapaaehtoista palauttamista ja sovinnollisen ratkaisun aikaansaamista lapsen palauttamiseksi. Edustusto avustaa lapsen huoltajan taikka muun lapsen huoltoon oikeutetun pyynnöstä ensisijaisesti tekemällä toimipiirinsä toimivaltaiselle viranomaiselle virka-apupyynnön: Edustusto avustaa asianosaisten välisessä yhteydenpidossa ja välittää lapsen palauttamista koskevia tietoja ja asiakirjoja viranomaisille ja lapsen palauttamista pyytäneelle. Edustusto avustaa lapsen kotiuttamisen järjestämisessä.",
      "section_number": "32",
      "chapter_number": 9,
      "statute_id": "50/1980"
    },
    {
      "id": "fe436c92-84a1-40b1-aea3-a5aebe94f478",
      "node_type": "Section",
      "publisher": "finlex",
      "title": "33 § Julkinen notaari edustustossa",
      "text": "Jäljempänä 34 §:ssä säädettyjä tehtäviä voi edustuston toimipiirissä suorittaa edustustossa palveleva avustaja tai hallinnollinen avustaja sekä virka-asemaltaan näitä korkeampi virkamies sekä muu ulkoasiainministeriön erityisestä syystä siihen valtuuttama edustustossa palveleva Suomen kansalainen. Ulkoasiainministeriön päätöksellä voidaan rajoittaa 1 momentissa tarkoitetun henkilön oikeutta suorittaa määrättyjä 34 §:n mukaisia tehtäviä. Kunniakonsuli voi toimialueellaan suorittaa niitä 34 §:ssä säädettyjä tehtäviä, joita suorittamaan ulkoasiainministeriö on hänet valtuuttanut.",
      "section_number": "33",
      "chapter_number": 10,
      "statute_id": "50/1980"
    },
    {
      "id": "6b137cdd-db03-4fa6-8fe1-e74e88b6c48a",
      "node_type": "Section",
      "publisher": "finlex",
      "title": "34 § Julkisen notaarin tehtävät edustustossa",
      "text": "Sellaisia tehtäviä, joita tarkoitetaan julkisesta notaarista annetussa laissa (287/1960) ja joita voidaan suorittaa edustustossa 2 §:n 1 momentissa tarkoitetun henkilön tai yhteisön pyynnöstä, ovat: Edustustossa voidaan lisäksi henkilön tai yhteisön pyynnöstä:",
      "section_number": "34",
      "chapter_number": 10,
      "statute_id": "50/1980"
    },
    {
      "id": "75355e97-b723-454b-ad9c-bb27b396f82a",
      "node_type": "Section",
      "publisher": "finlex",
      "title": "35 § Oikeus kieltäytyä toimenpiteestä",
      "text": "Edellä 34 §:ssä tarkoitetusta toimenpiteestä on oikeus kieltäytyä, jos asiakirjan tai muun selvityksen sisältö ei vastaa ulkoasiainministeriön tai edustuston tiedossa olevia tosiseikkoja tai jos on perusteltua syytä epäillä, että asiakirja, viranomaisen allekirjoitus tai viranomaisen antama todistus on väärennetty taikka asiakirja on laadittu käytettäväksi lainvastaiseen tarkoitukseen.",
      "section_number": "35",
      "chapter_number": 10,
      "statute_id": "50/1980"
    },
    {
      "id": "e683ddc0-19c1-4ec5-8751-bd1530ee02e1",
      "node_type": "Section",
      "publisher": "finlex",
      "title": "36 § Rekisterin pito ja käyttötarkoitus",
      "text": "Edustusto voi pitää henkilörekisteriä, jos se on välttämätöntä 4 luvussa tarkoitettujen henkilökohtaista turvallisuutta koskevien tehtävien suorittamiseksi. Edustusto päättää rekisterin perustamisesta. Edustuston henkilörekisteriin sovelletaan henkilötietojen suojaa koskevaa lainsäädäntöä, jollei tässä laissa toisin säädetä.",
      "section_number": "36",
      "chapter_number": 11,
      "statute_id": "50/1980"
    },
    {
      "id": "ae548eac-34f3-401c-87cf-668b465ab8bb",
      "node_type": "Section",
      "publisher": "finlex",
      "title": "37 § Henkilötietojen käsittely ja säilyttäminen",
      "text": "Edustustolla on oikeus käsitellä 4 luvussa tarkoitettujen tehtävien suorittamiseksi tarpeellisia tietoja sekä saada salassapitosäännösten estämättä tehtävien suorittamiseksi tarpeellisia tietoja muulta viranomaiselta, yhteisöltä tai henkilöltä. Tietojen käsittelyyn hankitaan rekisteröidyn suostumus, jollei suostumuksen hankkiminen ole mahdotonta tai siitä aiheutuisi kohtuutonta vaivaa. Rekisteröidyllä on oikeus kieltää häntä koskevien tietojen käsittely. Jos henkilörekisteri ei ole enää tarpeellinen 4 luvussa tarkoitettujen henkilökohtaista turvallisuutta koskevien tehtävien suorittamiseksi, rekisteri on hävitettävä, jollei siihen talletettuja tietoja ole erikseen säädetty säilytettäviksi tai arkistoitaviksi ulkoasiainhallinnon asiakirjojen arkistointia koskevien säännösten mukaisesti. Perustetta ja käsittelyn tarvetta on arvioitava vähintään viiden vuoden välein.",
      "section_number": "37",
      "chapter_number": 11,
      "statute_id": "50/1980"
    },
    {
      "id": "92f15bc9-f6f4-4954-8382-d93a324bc24d",
      "node_type": "Section",
      "publisher": "finlex",
      "title": "38 § Tietojen luovuttaminen ulkomaille",
      "text": "Edustusto saa luovuttaa henkilörekisteristä tietoja vieraan valtion viranomaiselle rekisteröidyn suostumuksella tai jos se on välttämätöntä rekisteröidyn elintärkeän edun suojaamiseksi.",
      "section_number": "38",
      "chapter_number": 11,
      "statute_id": "50/1980"
    },
    {
      "id": "7629f61b-b309-47de-a2d5-754a1a3cdc33",
      "node_type": "Section",
      "publisher": "finlex",
      "title": "39 § Konsulipalveluista perittävät maksut ja muut kustannukset",
      "text": "Konsulipalveluista perittävistä maksuista päättää ulkoasiainministeriö. Jos laissa ei toisin säädetä, ulkoasiainhallinto ei vastaa asian hoitamisesta aiheutuvista kustannuksista, jotka johtuvat esimerkiksi sairaanhoidosta, evakuoinnista, kotiuttamisesta, vainajan hautaamisesta, tuhkaamisesta tai kotiuttamisesta, oikeudenkäynnistä, oikeudenkäyntiavustajan tai oikeudellisen neuvonantajan palkkaamisesta, tulkkauksesta taikka asian hoitamiseksi tarvittavien asiakirjojen hankkimisesta ja käännättämisestä.",
      "section_number": "39",
      "chapter_number": 12,
      "statute_id": "50/1980"
    },
    {
      "id": "9a54dcb3-2945-4595-b2a5-638115e23d00",
      "node_type": "Section",
      "publisher": "finlex",
      "title": "40 § Edustuston ilmoitusvelvollisuus",
      "text": "Edustuston tulee ilmoittaa ulkoasiainministeriölle toimipiirissään 3―9 luvun mukaisen konsulipalveluasian vireilletulosta, jos asian luonne sitä vaatii. Jos asian kiireellisyyden vuoksi välitön ilmoittaminen ei ole mahdollista, asiasta on ilmoitettava heti, kun se on asian vaatimien välttämättömien ja kiireellisten toimenpiteiden jälkeen mahdollista.",
      "section_number": "40",
      "chapter_number": 12,
      "statute_id": "50/1980"
    },
    {
      "id": "98479f52-e039-411e-9b42-679d5a8b1209",
      "node_type": "Section",
      "publisher": "finlex",
      "title": "41 § Tietojen saaminen ja luovuttaminen",
      "text": "Sen lisäksi, mitä 37 ja 38 §:ssä säädetään tietojen saamisesta ja luovuttamisesta, ulkoasiainministeriöllä ja edustustolla on oikeus salassapitosäännösten estämättä saada tietoja muulta viranomaiselta, yhteisöltä tai henkilöltä ja luovuttaa tietoja Suomen tai vieraan valtion viranomaiselle tässä laissa tarkoitettujen konsulipalvelujen antamiseksi, kun se on välttämätöntä asianomaisen hengen, terveyden taikka fyysisen tai psyykkisen hyvinvoinnin kannalta.",
      "section_number": "41",
      "chapter_number": 12,
      "statute_id": "50/1980"
    },
    {
      "id": "f553052c-ff53-4871-a64f-d1170409a26d",
      "node_type": "Section",
      "publisher": "finlex",
      "title": "42 § Takaisinperintä",
      "text": "Tässä laissa tarkoitetut avustukset ja maksut, joiden suoritus on laiminlyöty, peritään ilman eri tuomiota tai päätöstä siten kuin verojen ja maksujen perimisestä ulosottotoimin annetussa laissa (367/1961) säädetään. Valtion varoista maksettu avustus voidaan kuitenkin jättää perimättä, jos henkilö, jolta se olisi perittävä, on varaton, tai perimättä jättämiseen on muu erityinen syy.",
      "section_number": "42",
      "chapter_number": 12,
      "statute_id": "50/1980"
    },
    {
      "id": "f289bdfd-19c9-4dbc-8fcf-8e85051ab1d0",
      "node_type": "Section",
      "publisher": "finlex",
      "title": "43 § Muutoksenhaku",
      "text": "Ulkoasiainministeriön tai edustuston tämän lain nojalla tekemään päätökseen haetaan muutosta valittamalla siten kuin muutoksenhausta hallintolainkäyttölaissa (586/1996) säädetään.",
      "section_number": "43",
      "chapter_number": 12,
      "statute_id": "50/1980"
    },
    {
      "id": "3b5e94e6-4476-479f-9fa0-3f8a9ddf6e08",
      "node_type": "Section",
      "publisher": "finlex",
      "title": "44 § Tarkemmat säännökset",
      "text": "Tarkemmat säännökset tämän lain täytäntöönpanosta annetaan tarvittaessa asetuksella.",
      "section_number": "44",
      "chapter_number": 12,
      "statute_id": "50/1980"
    },
    {
      "id": "336a65f0-4868-420f-a1d6-4ec02637cedc",
      "node_type": "Section",
      "publisher": "finlex",
      "title": "45 § Voimaantulo",
      "text": "Tämä laki tulee voimaan 1 päivänä joulukuuta 1999.",
      "section_number": "45",
      "chapter_number": 12,
      "statute_id": "50/1980"
    },
    {
      "id": "ace0003a-6abc-453d-bd34-064acbcad502",
      "node_type": "Section",
      "publisher": "finlex",
      "title": "46 § Siirtymäsäännös",
      "text": "Jos jäämistöasia on tullut vireille edustustossa tai ulkoasiainministeriössä ennen 1 päivää tammikuuta 2002, edustusto tai ulkoasiainministeriö voi avustaa perillisiä jäämistön selvittämiseen tarvittavien asiakirjojen hankkimisessa ja jäämistövarojen tilittämisessä perillisille.",
      "section_number": "46",
      "chapter_number": 12,
      "statute_id": "50/1980"
    }
  ],
  "clauses": [
    {
      "id": "52e10493-1a67-4b47-9b7f-a957a13fc3c1",
      "node_type": "Clause",
      "publisher": "finlex",
      "title": "§ 13 mom 1",
      "text": "1) vähäistä avustusta välittömän hädän poistamiseksi;",
      "clause_number": 1,
      "section_number": "13",
      "statute_id": "50/1980"
    },
    {
      "id": "b75ef752-32ca-4bf3-ab29-09c3bb8176c6",
      "node_type": "Clause",
      "publisher": "finlex",
      "title": "§ 13 mom 2",
      "text": "2) avustusta kotimatkaa varten takaisinmaksusitoumusta vastaan, jos talletuksen saaminen ei ole mahdollista; tai",
      "clause_number": 2,
      "section_number": "13",
      "statute_id": "50/1980"
    },
    {
      "id": "7033d023-50a0-40c5-9478-9b3ea7c5424f",
      "node_type": "Clause",
      "publisher": "finlex",
      "title": "§ 13 mom 3",
      "text": "3) avustusta kotimatkaa tai sairauden välttämätöntä ja tilapäistä hoitoa varten, jos talletuksen saaminen ei ole mahdollista eikä hädänalaisessa asemassa olevan ole mahdollista antaa takaisinmaksusitoumusta sairauden vakavuuden tai muun siihen verrattavan erityisen syyn vuoksi.",
      "clause_number": 3,
      "section_number": "13",
      "statute_id": "50/1980"
    },
    {
      "id": "41385dd2-9191-42c3-8251-2ac8b45546ea",
      "node_type": "Clause",
      "publisher": "finlex",
      "title": "§ 14 mom 1",
      "text": "1) hakija on avustusta hakiessaan tietoisesti antanut henkilöllisyyttään koskevia tai muita päätökseen vaikuttavia vääriä tietoja taikka salannut sellaisen seikan, joka olisi saattanut vaikuttaa päätöksen sisältöön;",
      "clause_number": 1,
      "section_number": "14",
      "statute_id": "50/1980"
    },
    {
      "id": "bd326fd4-ebee-412c-9d44-c4310fa02dd2",
      "node_type": "Clause",
      "publisher": "finlex",
      "title": "§ 14 mom 2",
      "text": "2) hakija on aikaisemmin saanut edustuston myöntämään perusteettomasti taloudellista avustusta antamalla tietoisesti henkilöllisyyttään koskevia tai päätökseen vaikuttaneita vääriä tietoja taikka salaamalla päätöksen sisältöön vaikuttaneita seikkoja;",
      "clause_number": 2,
      "section_number": "14",
      "statute_id": "50/1980"
    },
    {
      "id": "700fbf6f-39d4-4118-a7f1-8217efcd7578",
      "node_type": "Clause",
      "publisher": "finlex",
      "title": "§ 14 mom 3",
      "text": "3) hakija on käyttänyt hänelle aikaisemmin myönnettyä avustusta muuhun kuin myönnettyyn tarkoitukseen; tai",
      "clause_number": 3,
      "section_number": "14",
      "statute_id": "50/1980"
    },
    {
      "id": "9a928734-3976-4fc0-b005-5a8528224ca0",
      "node_type": "Clause",
      "publisher": "finlex",
      "title": "§ 14 mom 4",
      "text": "4) hakija ei ole maksanut takaisin hänelle aikaisemmin myönnettyä avustusta.",
      "clause_number": 4,
      "section_number": "14",
      "statute_id": "50/1980"
    },
    {
      "id": "40708e87-be00-4e3a-8795-495cc52bab5d",
      "node_type": "Clause",
      "publisher": "finlex",
      "title": "§ 31 mom 1",
      "text": "1) jos lapsi tai hänen palauttamistaan pyytävä huoltaja on Suomen kansalainen;",
      "clause_number": 1,
      "section_number": "31",
      "statute_id": "50/1980"
    },
    {
      "id": "193c4540-3dd9-4cd5-a9b3-36e52cc13804",
      "node_type": "Clause",
      "publisher": "finlex",
      "title": "§ 31 mom 2",
      "text": "2) jos lapsen poisviemistä tai palauttamatta jättämistä pidetään luvattomana sen valtion oikeusjärjestyksen mukaan, josta lapsi vietiin tai johon lapsi jätettiin palauttamatta; ja",
      "clause_number": 2,
      "section_number": "31",
      "statute_id": "50/1980"
    },
    {
      "id": "c9b33ecd-cac8-4a59-98db-993e7983d4f2",
      "node_type": "Clause",
      "publisher": "finlex",
      "title": "§ 31 mom 3",
      "text": "3) jos lapsen palauttamista koskevan asian hoitaminen ei kuulu muun viranomaisen toimivaltaan.",
      "clause_number": 3,
      "section_number": "31",
      "statute_id": "50/1980"
    },
    {
      "id": "47454dd2-0294-4d3c-ad96-1ee55084db43",
      "node_type": "Clause",
      "publisher": "finlex",
      "title": "§ 32 mom 1",
      "text": "1) lapsen olinpaikan ja hänen olosuhteittensa selvittämisestä sekä lapsen palauttamisesta;",
      "clause_number": 1,
      "section_number": "32",
      "statute_id": "50/1980"
    },
    {
      "id": "65a2a384-bffc-4423-a14d-bcc4d3b8ad99",
      "node_type": "Clause",
      "publisher": "finlex",
      "title": "§ 32 mom 2",
      "text": "2) paikallisen lainsäädännön mukaisen oikeusavustajan ja muun oikeusavun saamisesta lapsen palauttamista pyytäneelle; sekä",
      "clause_number": 2,
      "section_number": "32",
      "statute_id": "50/1980"
    },
    {
      "id": "8b71cee3-9306-4698-b05d-bdf27a16154b",
      "node_type": "Clause",
      "publisher": "finlex",
      "title": "§ 32 mom 3",
      "text": "3) yleisluontoisten tietojen hankkimisesta asianomaisen valtion lainsäädännöstä tarpeellisilta osin.",
      "clause_number": 3,
      "section_number": "32",
      "statute_id": "50/1980"
    },
    {
      "id": "55d453b9-3595-4ef7-91f1-198470f61113",
      "node_type": "Clause",
      "publisher": "finlex",
      "title": "§ 34 mom 1",
      "text": "1) allekirjoituksen oikeaksi todistaminen;",
      "clause_number": 1,
      "section_number": "34",
      "statute_id": "50/1980"
    },
    {
      "id": "4f3df887-2f1c-410d-9367-007a8eda581d",
      "node_type": "Clause",
      "publisher": "finlex",
      "title": "§ 34 mom 2",
      "text": "2) jäljennöksen oikeaksi todistaminen asiakirjasta; sekä",
      "clause_number": 2,
      "section_number": "34",
      "statute_id": "50/1980"
    },
    {
      "id": "834d4a6d-873c-4c8b-8bbc-d061b30cf415",
      "node_type": "Clause",
      "publisher": "finlex",
      "title": "§ 34 mom 3",
      "text": "3) todistuksen antaminen esitetyn asiakirjan sisällöstä.",
      "clause_number": 3,
      "section_number": "34",
      "statute_id": "50/1980"
    },
    {
      "id": "9e5910ca-166f-4730-9995-cb6bf2dc854d",
      "node_type": "Clause",
      "publisher": "finlex",
      "title": "§ 34 mom 1",
      "text": "1) antaa esitetyn selvityksen perusteella elossaolotodistus tai todistus asiantilasta;",
      "clause_number": 1,
      "section_number": "34",
      "statute_id": "50/1980"
    },
    {
      "id": "c3baf559-e351-49c2-bc4c-6caf68836f11",
      "node_type": "Clause",
      "publisher": "finlex",
      "title": "§ 34 mom 2",
      "text": "2) todistaa, jos Suomea sitova kansainvälinen sopimus ei sitä estä, edustuston toimipiirin viranomaisen antamassa asiakirjassa tai todistuksessa oleva allekirjoitus ja allekirjoittajan virka-asema oikeaksi, jos edustustolla on asianmukainen nimikirjoitusnäyte, tieto hänen virka-asemastaan sekä viranomaisen leimanäyte;",
      "clause_number": 2,
      "section_number": "34",
      "statute_id": "50/1980"
    },
    {
      "id": "8b5d0309-969a-49d9-a295-a9ac26734f86",
      "node_type": "Clause",
      "publisher": "finlex",
      "title": "§ 34 mom 1",
      "text": "3) todistaa perustellusta syystä, että ulkoasiainministeriön julkisesta notaarista annetun lain 7 §:n 1 momentin nojalla antaman todistuksen allekirjoittajalla on asiakirjassa mainittu virka-asema ja että hänellä on ollut laillinen oikeus antaa sellainen todistus; sekä",
      "clause_number": 1,
      "section_number": "34",
      "statute_id": "50/1980"
    },
    {
      "id": "91d53f65-1728-47a9-aa49-15ee6f95a4e4",
      "node_type": "Clause",
      "publisher": "finlex",
      "title": "§ 34 mom 3",
      "text": "3) todistaa perustellusta syystä, että ulkoasiainministeriön julkisesta notaarista annetun lain 7 §:n 1 momentin nojalla antaman todistuksen allekirjoittajalla on asiakirjassa mainittu virka-asema ja että hänellä on ollut laillinen oikeus antaa sellainen todistus; sekä",
      "clause_number": 3,
      "section_number": "34",
      "statute_id": "50/1980"
    },
    {
      "id": "d905f368-380e-4e29-95dd-b6625aba6379",
      "node_type": "Clause",
      "publisher": "finlex",
      "title": "§ 34 mom 4",
      "text": "4) suorittaa ne muut toimenpiteet, jotka ulkomailla kuuluvat edustustolle tai edustuston virkamiehelle lain, asetuksen tai Suomea sitovan kansainvälisen sopimuksen mukaan.",
      "clause_number": 4,
      "section_number": "34",
      "statute_id": "50/1980"
    }
  ],
  "cross_references": [],
  "raw_html_path": "C:\\Users\\danit\\finance-hack\\aalto-hackaton-2026\\data\\raw\\finlex\\Laki (säädöskokoelma)\\Konsulipalvelulaki.html"
}