{
  "statute": {
    "id": "7bfb80cb-17d6-4344-9c1d-d0c82bfb5b7d",
    "node_type": "Statute",
    "publisher": "finlex",
    "title": "Asetus Venäjän ja Itä-Euroopan instituutista annetun asetuksen 7 §:n muuttamisesta",
    "text": "Asetus Venäjän ja Itä-Euroopan instituutista annetun asetuksen 7 §:n muuttamisesta",
    "statute_id": "858/1992",
    "finlex_url": "https://finlex.fi/fi/laki/ajantasa/858/1992"
  },
  "chapters": [],
  "sections": [
    {
      "id": "ba8e8f64-1597-4b4c-8e18-b2542ab17fb9",
      "node_type": "Section",
      "publisher": "finlex",
      "title": "7 §",
      "text": "Johtajan erityisenä kelpoisuusvaatimuksena on ylempi korkeakoulututkinto, instituutin tehtävien hyvä tuntemus, perehtyneisyys hallintotehtäviin, käytännössä osoitettu johtamistaito sekä hyvä venäjän kielen taito. Tämä asetus tulee voimaan 1 päivänä joulukuuta 1997.",
      "section_number": "7",
      "chapter_number": 1,
      "statute_id": "858/1992"
    }
  ],
  "clauses": [],
  "cross_references": [],
  "raw_html_path": "C:\\Users\\danit\\finance-hack\\aalto-hackaton-2026\\data\\raw\\finlex\\Asetus\\Asetus Venäjän ja Itä-Euroopan instituutista annetun asetuksen 7 §_n muuttamisesta.html"
}