{
  "statute": {
    "id": "b54a6546-f052-4308-bb29-4ccda0e73cb7",
    "node_type": "Statute",
    "publisher": "finlex",
    "title": "KHO:1983-B-II-616",
    "text": "KHO:1983-B-II-616",
    "statute_id": "873/1981",
    "finlex_url": "https://finlex.fi/fi/laki/ajantasa/873/1981"
  },
  "chapters": [],
  "sections": [
    {
      "id": "cd097746-3273-46e0-8656-bf5714fd6819",
      "node_type": "Section",
      "publisher": "finlex",
      "title": "KHO:1983-B-II-616",
      "text": "Yhtiö harjoitti tietokonekauppaa pitkäaikaisen vuokrauksen muodossa. Vuokratut koneet oli yhtiön kirjanpidossa kirjattu käyttöomaisuudeksi ja niistä oli tehty poistot. Po. koneiden poistot oli otettava huomioon määrättäessä yhtiön sosiaaliturvamaksun suuruutta. Verovuosi_1982 A työnantajan sosiaaliturvamaksusta 1 § (873/1981)\n                    KansaneläkeL 3 §",
      "section_number": "1",
      "chapter_number": 1,
      "statute_id": "873/1981"
    }
  ],
  "clauses": [],
  "cross_references": [],
  "raw_html_path": "C:\\Users\\danit\\finance-hack\\aalto-hackaton-2026\\data\\raw\\finlex\\Korkein hallinto-oikeus_ Ennakkopäätökset\\KHO_1983-B-II-616.html"
}